py_xml_ccda/__init__.py
py_xml_ccda/main.py
py_xml_ccda/utils.py
py_xml_ccda-1.0.0.dist-info/METADATA
py_xml_ccda-1.0.0.dist-info/WHEEL
py_xml_ccda-1.0.0.dist-info/entry_points.txt
py_xml_ccda-1.0.0.dist-info/top_level.txt
py_xml_ccda-1.0.0.dist-info/RECORD
