Metadata-Version: 2.4
Name: py_xml_ccda
Version: 1.0.0
Dynamic: description
Dynamic: description-content-type
